argparsh/__init__.py
argparsh/__main__.py
argparsh/main.py
argparsh/utils.py
argparsh-0.0.4.dist-info/METADATA
argparsh-0.0.4.dist-info/WHEEL
argparsh-0.0.4.dist-info/entry_points.txt
argparsh-0.0.4.dist-info/licenses/LICENSE
argparsh-0.0.4.dist-info/RECORD
