Metadata-Version: 2.3
Name: argparsh
Version: 0.0.4
Summary: Argparse for shell scripts
Project-URL: Homepage, https://github.com/aneeshdurg/argparsh
Project-URL: Bug Tracker, https://github.com/aneeshdurg/argparsh/issues
Author-email: Aneesh Durg <aneeshdurg17@gmail.com>
Classifier: Intended Audience :: Developers
Classifier: License :: OSI Approved :: MIT License
Classifier: Operating System :: OS Independent
Classifier: Programming Language :: Python :: 3
Requires-Python: >=3.10
